runner.py
python_script_runner-7.0.5.dist-info/licenses/LICENSE
python_script_runner-7.0.5.dist-info/METADATA
python_script_runner-7.0.5.dist-info/WHEEL
python_script_runner-7.0.5.dist-info/entry_points.txt
python_script_runner-7.0.5.dist-info/top_level.txt
python_script_runner-7.0.5.dist-info/RECORD
