Metadata-Version: 2.4
Name: python-script-runner
Version: 7.0.5
Summary: Production-grade Python script execution engine with comprehensive monitoring, alerting, analytics, and enterprise integrations
Home-page: https://github.com/jomardyan/Python-Script-Runner
Author: Python Script Runner Contributors
License: MIT
Project-URL: Homepage, https://github.com/jomardyan/Python-Script-Runner
Project-URL: Documentation, https://github.com/jomardyan/Python-Script-Runner#readme
Project-URL: Repository, https://github.com/jomardyan/Python-Script-Runner.git
Project-URL: Bug Tracker, https://github.com/jomardyan/Python-Script-Runner/issues
Keywords: python,script,runner,monitoring,alerting,analytics,performance,ci-cd
Classifier: Development Status :: 5 - Production/Stable
Classifier: Intended Audience :: Developers
Classifier: Intended Audience :: System Administrators
Classifier: License :: OSI Approved :: MIT License
Classifier: Programming Language :: Python :: 3
Classifier: Programming Language :: Python :: 3.6
Classifier: Programming Language :: Python :: 3.7
Classifier: Programming Language :: Python :: 3.8
Classifier: Programming Language :: Python :: 3.9
Classifier: Programming Language :: Python :: 3.10
Classifier: Programming Language :: Python :: 3.11
Classifier: Programming Language :: Python :: Implementation :: CPython
Classifier: Programming Language :: Python :: Implementation :: PyPy
Classifier: Topic :: Software Development
Classifier: Topic :: System :: Monitoring
Requires-Python: >=3.6
License-File: LICENSE
Requires-Dist: psutil>=5.9.0
Requires-Dist: pyyaml>=6.0
Requires-Dist: requests>=2.31.0
Provides-Extra: dashboard
Requires-Dist: fastapi>=0.104.0; extra == "dashboard"
Requires-Dist: uvicorn[standard]>=0.24.0; extra == "dashboard"
Requires-Dist: websockets>=12.0; extra == "dashboard"
Provides-Extra: export
Requires-Dist: pyarrow>=13.0.0; extra == "export"
Requires-Dist: scikit-learn>=1.3.0; extra == "export"
Provides-Extra: otel
Requires-Dist: opentelemetry-api>=1.20.0; extra == "otel"
Requires-Dist: opentelemetry-sdk>=1.20.0; extra == "otel"
Requires-Dist: opentelemetry-exporter-jaeger>=1.20.0; extra == "otel"
Requires-Dist: opentelemetry-instrumentation>=0.41b0; extra == "otel"
Provides-Extra: security
Requires-Dist: bandit>=1.7.5; extra == "security"
Requires-Dist: semgrep>=1.45.0; extra == "security"
Requires-Dist: safety>=2.3.0; extra == "security"
Requires-Dist: detect-secrets>=1.4.0; extra == "security"
Requires-Dist: cyclonedx-python>=4.0.0; extra == "security"
Provides-Extra: cloud
Requires-Dist: boto3>=1.28.0; extra == "cloud"
Requires-Dist: azure-identity>=1.13.0; extra == "cloud"
Requires-Dist: google-cloud-compute>=1.13.0; extra == "cloud"
Requires-Dist: google-cloud-monitoring>=2.15.0; extra == "cloud"
Provides-Extra: vault
Requires-Dist: hvac>=1.2.0; extra == "vault"
Provides-Extra: all
Requires-Dist: fastapi>=0.104.0; extra == "all"
Requires-Dist: uvicorn[standard]>=0.24.0; extra == "all"
Requires-Dist: websockets>=12.0; extra == "all"
Requires-Dist: pyarrow>=13.0.0; extra == "all"
Requires-Dist: scikit-learn>=1.3.0; extra == "all"
Requires-Dist: opentelemetry-api>=1.20.0; extra == "all"
Requires-Dist: opentelemetry-sdk>=1.20.0; extra == "all"
Requires-Dist: opentelemetry-exporter-jaeger>=1.20.0; extra == "all"
Requires-Dist: opentelemetry-instrumentation>=0.41b0; extra == "all"
Requires-Dist: bandit>=1.7.5; extra == "all"
Requires-Dist: semgrep>=1.45.0; extra == "all"
Requires-Dist: safety>=2.3.0; extra == "all"
Requires-Dist: detect-secrets>=1.4.0; extra == "all"
Requires-Dist: cyclonedx-python>=4.0.0; extra == "all"
Requires-Dist: boto3>=1.28.0; extra == "all"
Requires-Dist: azure-identity>=1.13.0; extra == "all"
Requires-Dist: google-cloud-compute>=1.13.0; extra == "all"
Requires-Dist: google-cloud-monitoring>=2.15.0; extra == "all"
Requires-Dist: hvac>=1.2.0; extra == "all"
Provides-Extra: dev
Requires-Dist: pytest>=7.0.0; extra == "dev"
Requires-Dist: pytest-cov>=4.0.0; extra == "dev"
Requires-Dist: black>=22.0.0; extra == "dev"
Requires-Dist: flake8>=4.0.0; extra == "dev"
Requires-Dist: mypy>=0.900; extra == "dev"
Provides-Extra: docs
Requires-Dist: mkdocs>=1.4.0; extra == "docs"
Requires-Dist: mkdocs-material>=9.0.0; extra == "docs"
Dynamic: home-page
Dynamic: license-file
Dynamic: requires-python
